<?xml version="1.0" encoding="UTF-8"?>
<!DOCTYPE node PUBLIC "-//freedesktop//DTD D-BUS Object Introspection 1.0//EN" "http://www.freedesktop.org/standards/dbus/1.0/introspect.dtd">
<node name="/">
  <fso:errordomain xmlns:fso="http://www.freesmartphone.org/schemas/DBusSpecExtension" name="org.freesmartphone.GSM" fso:no-container="true">
    <error name="DeviceNotPresent"/>
    <error name="DeviceTimeout"/>
    <error name="DeviceFailed"/>
    <error name="SimNotPresent"/>
    <error name="SimAuthFailed"/>
    <error name="SimBlocked"/>
    <error name="SimNotFound"/>
    <error name="SimMemoryFull"/>
    <error name="SimInvalidIndex"/>
    <error name="CallNotFound"/>
    <error name="MuxChannelTaken"/>
    <error name="MuxNoChannel"/>
    <error name="MuxNoSession"/>
    <error name="MuxSessionAlreadyOpen"/>
    <error name="MuxSessionOpenError"/>
    <error name="NetworkNotPresent"/>
    <error name="NetworkUnauthorized"/>
    <error name="NetworkNotSupported"/>
    <error name="NetworkNotFound"/>
    <error name="ContextNotFound"/>
  </fso:errordomain>
</node>
